mautrix_telegram/__init__.py
mautrix_telegram/__main__.py
mautrix_telegram/abstract_user.py
mautrix_telegram/bot.py
mautrix_telegram/config.py
mautrix_telegram/example-config.yaml
mautrix_telegram/get_version.py
mautrix_telegram/matrix.py
mautrix_telegram/portal.py
mautrix_telegram/puppet.py
mautrix_telegram/tgclient.py
mautrix_telegram/types.py
mautrix_telegram/unicodemojipack.pickle
mautrix_telegram/user.py
mautrix_telegram/version.py
mautrix_telegram/commands/__init__.py
mautrix_telegram/commands/handler.py
mautrix_telegram/commands/matrix_auth.py
mautrix_telegram/commands/portal/__init__.py
mautrix_telegram/commands/portal/admin.py
mautrix_telegram/commands/portal/bridge.py
mautrix_telegram/commands/portal/config.py
mautrix_telegram/commands/portal/create_chat.py
mautrix_telegram/commands/portal/filter.py
mautrix_telegram/commands/portal/misc.py
mautrix_telegram/commands/portal/unbridge.py
mautrix_telegram/commands/portal/util.py
mautrix_telegram/commands/telegram/__init__.py
mautrix_telegram/commands/telegram/account.py
mautrix_telegram/commands/telegram/auth.py
mautrix_telegram/commands/telegram/misc.py
mautrix_telegram/db/__init__.py
mautrix_telegram/db/backfill_queue.py
mautrix_telegram/db/bot_chat.py
mautrix_telegram/db/disappearing_message.py
mautrix_telegram/db/message.py
mautrix_telegram/db/portal.py
mautrix_telegram/db/puppet.py
mautrix_telegram/db/reaction.py
mautrix_telegram/db/telegram_file.py
mautrix_telegram/db/telethon_session.py
mautrix_telegram/db/user.py
mautrix_telegram/db/upgrade/__init__.py
mautrix_telegram/db/upgrade/v00_latest_revision.py
mautrix_telegram/db/upgrade/v01_initial_revision.py
mautrix_telegram/db/upgrade/v02_sponsored_events.py
mautrix_telegram/db/upgrade/v03_reactions.py
mautrix_telegram/db/upgrade/v04_disappearing_messages.py
mautrix_telegram/db/upgrade/v05_channel_ghosts.py
mautrix_telegram/db/upgrade/v06_puppet_avatar_url.py
mautrix_telegram/db/upgrade/v07_puppet_phone_number.py
mautrix_telegram-0.15.3.dist-info/LICENSE
mautrix_telegram-0.15.3.dist-info/METADATA
mautrix_telegram-0.15.3.dist-info/WHEEL
mautrix_telegram-0.15.3.dist-info/top_level.txt
mautrix_telegram-0.15.3.dist-info/RECORD
