Metadata-Version: 2.2
Name: mautrix-telegram
Version: 0.15.3
Summary: A Matrix-Telegram hybrid puppeting/relaybot bridge.
Home-page: https://github.com/mautrix/telegram
Author: Tulir Asokan
Author-email: tulir@maunium.net
Project-URL: Changelog, https://github.com/mautrix/telegram/blob/master/CHANGELOG.md
Classifier: Development Status :: 4 - Beta
Classifier: License :: OSI Approved :: GNU Affero General Public License v3 or later (AGPLv3+)
Classifier: Topic :: Communications :: Chat
Classifier: Framework :: AsyncIO
Classifier: Programming Language :: Python
Classifier: Programming Language :: Python :: 3
Classifier: Programming Language :: Python :: 3.10
Classifier: Programming Language :: Python :: 3.11
Classifier: Programming Language :: Python :: 3.12
Classifier: Programming Language :: Python :: 3.13
Requires-Python: ~=3.10
License-File: LICENSE
Requires-Dist: ruamel.yaml<0.19,>=0.15.35
Requires-Dist: python-magic<0.5,>=0.4
Requires-Dist: commonmark<0.10,>=0.8
Requires-Dist: aiohttp<4,>=3
Requires-Dist: yarl<2,>=1
Requires-Dist: mautrix<0.21,>=0.20.8
Requires-Dist: tulir-telethon==1.99.0a6
Requires-Dist: asyncpg<1,>=0.20
Requires-Dist: mako<2,>=1
Requires-Dist: setuptools
Provides-Extra: speedups
Requires-Dist: aiodns; extra == "speedups"
Requires-Dist: brotli; extra == "speedups"
Requires-Dist: cryptg<0.6,>=0.1; extra == "speedups"
Provides-Extra: qr-login
Requires-Dist: pillow<12,>=10.0.1; extra == "qr-login"
Requires-Dist: qrcode<9,>=6; extra == "qr-login"
Provides-Extra: formattednumbers
Requires-Dist: phonenumbers<10,>=8; extra == "formattednumbers"
Provides-Extra: metrics
Requires-Dist: prometheus_client<0.23,>=0.6; extra == "metrics"
Provides-Extra: e2be
Requires-Dist: pycryptodome<4,>=3; extra == "e2be"
Requires-Dist: python-olm<4,>=3; extra == "e2be"
Requires-Dist: unpaddedbase64<3,>=1; extra == "e2be"
Provides-Extra: sqlite
Requires-Dist: aiosqlite<0.22,>=0.16; extra == "sqlite"
Provides-Extra: proxy
Requires-Dist: python-socks[asyncio]; extra == "proxy"
Provides-Extra: all
Requires-Dist: aiodns; extra == "all"
Requires-Dist: aiosqlite<0.22,>=0.16; extra == "all"
Requires-Dist: brotli; extra == "all"
Requires-Dist: cryptg<0.6,>=0.1; extra == "all"
Requires-Dist: phonenumbers<10,>=8; extra == "all"
Requires-Dist: pillow<12,>=10.0.1; extra == "all"
Requires-Dist: prometheus_client<0.23,>=0.6; extra == "all"
Requires-Dist: pycryptodome<4,>=3; extra == "all"
Requires-Dist: python-olm<4,>=3; extra == "all"
Requires-Dist: python-socks[asyncio]; extra == "all"
Requires-Dist: qrcode<9,>=6; extra == "all"
Requires-Dist: unpaddedbase64<3,>=1; extra == "all"
Dynamic: author
Dynamic: author-email
Dynamic: classifier
Dynamic: description
Dynamic: description-content-type
Dynamic: home-page
Dynamic: project-url
Dynamic: provides-extra
Dynamic: requires-dist
Dynamic: requires-python
Dynamic: summary
